OBSV_tools/Combine_fig_MS.py
OBSV_tools/Combine_fig_ppt.py
OBSV_tools/Combine_method_SI.py
OBSV_tools/Combine_multi_conf.py
OBSV_tools/Plot_Ene.py
OBSV_tools/pml_str.py
OBSV_tools/write_run_pml.py
OBSV_tools-1.0.15.dist-info/METADATA
OBSV_tools-1.0.15.dist-info/WHEEL
OBSV_tools-1.0.15.dist-info/entry_points.txt
OBSV_tools-1.0.15.dist-info/top_level.txt
OBSV_tools-1.0.15.dist-info/RECORD
