Metadata-Version: 2.1
Name: OBSV-tools
Version: 1.0.15
Summary: Tools for ONIOM-based Strain Visualisation
Home-page: 
Author-email: yanzy@sustech.edu.cn
Requires-Python: ~=3.9
